README.md
setup.py
autotec/__init__.py
autotec/api_client.py
autotec/configuration.py
autotec/rest.py
autotec/api/__init__.py
autotec/api/vehicle_api.py
autotec/models/__init__.py
autotec/models/history_record.py
autotec/models/history_request.py
autotec/models/history_response.py
autotec/models/risk_calculation_request.py
autotec/models/risk_calculation_response.py
autotec/models/vehicle.py
autotec/models/vehicle_history.py
autotec/models/vehicle_information.py
autotec/models/vehicle_ownership_activity.py
autotec/models/vehicle_request_attribute.py
autotec/models/vehicle_risk_request_attribute.py
autotec/models/vehicle_risk_result.py
autotec/models/vehicle_scoring.py
autotec_api_python_client.egg-info/PKG-INFO
autotec_api_python_client.egg-info/SOURCES.txt
autotec_api_python_client.egg-info/dependency_links.txt
autotec_api_python_client.egg-info/requires.txt
autotec_api_python_client.egg-info/top_level.txt
test/__init__.py
test/test_history_record.py
test/test_history_request.py
test/test_history_response.py
test/test_risk_calculation_request.py
test/test_risk_calculation_response.py
test/test_vehicle.py
test/test_vehicle_api.py
test/test_vehicle_history.py
test/test_vehicle_information.py
test/test_vehicle_ownership_activity.py
test/test_vehicle_request_attribute.py
test/test_vehicle_risk_request_attribute.py
test/test_vehicle_risk_result.py
test/test_vehicle_scoring.py