Metadata-Version: 1.0
Name: autotec-api-python-client
Version: 1.0.30
Summary: AutoTec Services API
Home-page: https://www.autotec.com
Author: UNKNOWN
Author-email: bitbucket@autotec.com
License: UNKNOWN
Keywords: Swagger,AutoTec Services API
Platform: UNKNOWN
